{"data":[{"id":"MDEwOlJlcG9zaXRvcnkzMTAyMzAyNTY=","name":"Native-apps","updatedAt":"2020-11-18T07:57:46Z","forkCount":0,"stargazerCount":0,"languages":[{"name":"JavaScript","iconifyClass":"logos-javascript"},{"name":"Java","iconifyClass":"logos-java"}]},{"id":"MDEwOlJlcG9zaXRvcnkzMDg4ODMwODE=","name":"cozzbie-challenge","updatedAt":"2020-11-01T21:29:06Z","forkCount":0,"stargazerCount":0,"languages":[{"name":"HTML","iconifyClass":"logos-html-5"},{"name":"CSS","iconifyClass":"logos-css-3"},{"name":"JavaScript","iconifyClass":"logos-javascript"}]},{"id":"MDEwOlJlcG9zaXRvcnkzMDIzMDQzMzk=","name":"todo-goals","updatedAt":"2020-10-08T10:23:40Z","forkCount":0,"stargazerCount":0,"languages":[]},{"id":"MDEwOlJlcG9zaXRvcnkzMDIyNzc3ODA=","name":"reactnd-chirper-app","updatedAt":"2020-10-08T08:50:19Z","forkCount":0,"stargazerCount":0,"languages":[{"name":"HTML","iconifyClass":"logos-html-5"},{"name":"JavaScript","iconifyClass":"logos-javascript"},{"name":"CSS","iconifyClass":"logos-css-3"}]},{"id":"MDEwOlJlcG9zaXRvcnkzMDIyNzY5NTE=","name":"dev-portfolio","updatedAt":"2020-10-13T20:48:17Z","forkCount":0,"stargazerCount":0,"languages":[{"name":"JavaScript","iconifyClass":"logos-javascript"},{"name":"CSS","iconifyClass":"logos-css-3"}]},{"id":"MDEwOlJlcG9zaXRvcnkyOTY1OTI2NTY=","name":"would-you-rather","updatedAt":"2020-10-30T10:03:56Z","forkCount":0,"stargazerCount":0,"languages":[{"name":"HTML","iconifyClass":"logos-html-5"},{"name":"JavaScript","iconifyClass":"logos-javascript"},{"name":"CSS","iconifyClass":"logos-css-3"}]},{"id":"MDEwOlJlcG9zaXRvcnkyOTEzMzY4NjI=","name":"Todo-List-App","updatedAt":"2020-09-08T19:08:59Z","forkCount":0,"stargazerCount":0,"languages":[{"name":"HTML","iconifyClass":"logos-html-5"}]},{"id":"MDEwOlJlcG9zaXRvcnkyODk3NDY1NjA=","name":"Portfolio","updatedAt":"2020-08-28T22:23:47Z","forkCount":0,"stargazerCount":0,"languages":[{"name":"JavaScript","iconifyClass":"logos-javascript"},{"name":"CSS","iconifyClass":"logos-css-3"}]},{"id":"MDEwOlJlcG9zaXRvcnkyODc0OTYzNTE=","name":"myreads-bookshelf-app","updatedAt":"2020-08-27T16:19:03Z","forkCount":0,"stargazerCount":0,"languages":[{"name":"HTML","iconifyClass":"logos-html-5"},{"name":"CSS","iconifyClass":"logos-css-3"},{"name":"JavaScript","iconifyClass":"logos-javascript"}]},{"id":"MDEwOlJlcG9zaXRvcnkyODU4MDMxNTU=","name":"contactList","updatedAt":"2020-08-07T10:33:28Z","forkCount":0,"stargazerCount":0,"languages":[]},{"id":"MDEwOlJlcG9zaXRvcnkyNjc4NTkyNTI=","name":"Store","updatedAt":"2020-08-23T11:12:36Z","forkCount":0,"stargazerCount":0,"languages":[{"name":"HTML","iconifyClass":"logos-html-5"},{"name":"CSS","iconifyClass":"logos-css-3"},{"name":"JavaScript","iconifyClass":"logos-javascript"}]},{"id":"MDEwOlJlcG9zaXRvcnkyNjA5NTAyMzk=","name":"Fashion_Store","updatedAt":"2020-10-13T17:41:30Z","forkCount":0,"stargazerCount":0,"languages":[{"name":"JavaScript","iconifyClass":"logos-javascript"},{"name":"CSS","iconifyClass":"logos-css-3"}]},{"id":"MDEwOlJlcG9zaXRvcnkyNTMwMTc2MzU=","name":"horeca-cloud","updatedAt":"2020-04-04T14:28:58Z","forkCount":0,"stargazerCount":0,"languages":[{"name":"HTML","iconifyClass":"logos-html-5"},{"name":"JavaScript","iconifyClass":"logos-javascript"},{"name":"CSS","iconifyClass":"logos-css-3"}]},{"id":"MDEwOlJlcG9zaXRvcnkyNTI5NzQwOTQ=","name":"Treva","updatedAt":"2020-04-04T11:04:26Z","forkCount":0,"stargazerCount":0,"languages":[]},{"id":"MDEwOlJlcG9zaXRvcnkyNDc5MDE0NzQ=","name":"Goggle-clone","updatedAt":"2020-09-21T23:38:15Z","forkCount":0,"stargazerCount":0,"languages":[{"name":"HTML","iconifyClass":"logos-html-5"},{"name":"CSS","iconifyClass":"logos-css-3"},{"name":"JavaScript","iconifyClass":"logos-javascript"}]},{"id":"MDEwOlJlcG9zaXRvcnkyNDQ5NDQ3NjU=","name":"React-Shopping-Cart","updatedAt":"2020-03-04T16:09:03Z","forkCount":0,"stargazerCount":0,"languages":[{"name":"HTML","iconifyClass":"logos-html-5"},{"name":"JavaScript","iconifyClass":"logos-javascript"},{"name":"CSS","iconifyClass":"logos-css-3"}]},{"id":"MDEwOlJlcG9zaXRvcnkyMzc0MjA2Njc=","name":"cleveroad","updatedAt":"2020-01-31T12:09:16Z","forkCount":0,"stargazerCount":0,"languages":[{"name":"HTML","iconifyClass":"logos-html-5"},{"name":"CSS","iconifyClass":"logos-css-3"},{"name":"JavaScript","iconifyClass":"logos-javascript"}]},{"id":"MDEwOlJlcG9zaXRvcnkyMzExMTY2NzQ=","name":"sijapp","updatedAt":"2020-11-01T09:30:36Z","forkCount":0,"stargazerCount":0,"languages":[{"name":"HTML","iconifyClass":"logos-html-5"},{"name":"CSS","iconifyClass":"logos-css-3"},{"name":"JavaScript","iconifyClass":"logos-javascript"}]},{"id":"MDEwOlJlcG9zaXRvcnkyMjUzOTg5NjA=","name":"internia","updatedAt":"2019-12-22T13:33:43Z","forkCount":0,"stargazerCount":0,"languages":[{"name":"HTML","iconifyClass":"logos-html-5"},{"name":"JavaScript","iconifyClass":"logos-javascript"},{"name":"CSS","iconifyClass":"logos-css-3"}]},{"id":"MDEwOlJlcG9zaXRvcnkxOTU4ODAzMDc=","name":"The-Wine-Shop-Content-Slider","updatedAt":"2019-07-08T20:17:20Z","forkCount":0,"stargazerCount":0,"languages":[{"name":"HTML","iconifyClass":"logos-html-5"},{"name":"CSS","iconifyClass":"logos-css-3"}]}]}